rws_py/__init__.py
rws_py/analysis_universal.py
rws_py/analyze_weather_load_storage.py
rws_py/config.py
rws_py/Cuxhaven-Solar-2020-describe.csv
rws_py/data/10minutenwerte_SOLAR_00891_20200101_20231231_hist.zip
rws_py/data/2024_Bertsch_residual_Load.csv
rws_py/data/2024_Bertsch_residual_Load.xlsx
rws_py/data/stations_data.csv
rws_py/dwd_analyze_store_second_threshold.py
rws_py/help_funcs.py
rws_py/la-plot.png
rws_py/load_curve_simple.py
rws_py/residual_analyse.py
rws_py/run_residual_store.py
rws_py/run_weather_load_store.py
rws_py/test_wind_data.zip
rws_py/test_wind_load_power.py
rws_py/utils/__init__.py
rws_py/utils/folder_to_hdf5.py
rws_py-0.2.2.post2.dist-info/AUTHORS.rst
rws_py-0.2.2.post2.dist-info/LICENSE
rws_py-0.2.2.post2.dist-info/METADATA
rws_py-0.2.2.post2.dist-info/WHEEL
rws_py-0.2.2.post2.dist-info/RECORD
